playfast-0.5.0.dist-info/METADATA
playfast-0.5.0.dist-info/WHEEL
playfast-0.5.0.dist-info/entry_points.txt
playfast-0.5.0.dist-info/licenses/LICENSE
playfast/__init__.py
playfast/batch.py
playfast/batch_builder.py
playfast/client.py
playfast/constants.py
playfast/core.abi3.so
playfast/core.pyi
playfast/exceptions.py
playfast/models.py
playfast/py.typed
playfast/rust_client.py
playfast-0.5.0.dist-info/RECORD
