Metadata-Version: 2.4
Name: playfast
Version: 0.5.0
Classifier: Development Status :: 4 - Beta
Classifier: Intended Audience :: Developers
Classifier: License :: OSI Approved :: MIT License
Classifier: Programming Language :: Python :: 3.11
Classifier: Programming Language :: Python :: 3.12
Classifier: Programming Language :: Python :: 3.13
Classifier: Programming Language :: Python :: 3.14
Classifier: Programming Language :: Rust
Classifier: Framework :: AsyncIO
Classifier: Framework :: Pydantic
Classifier: Topic :: Software Development :: Libraries :: Python Modules
Requires-Dist: aiohttp>=3.13.0
Requires-Dist: pydantic>=2.12.0
License-File: LICENSE
Summary: Playfast - Lightning-Fast Google Play Store Scraper
Keywords: google-play,scraper,async,rust,pyo3,performance,free-threading
Author-email: Taeyun Jang <taeyun16@pm.me>
License: MIT
Requires-Python: >=3.11
Project-URL: source, https://github.com/mixL1nk/playfast
Project-URL: documentation, https://mixl1nk.github.io/playfast/
Project-URL: changelog, https://github.com/mixL1nk/playfast/blob/master/CHANGELOG.md
